AUTHORS
CHANGES.rst
LICENSE
MANIFEST.in
README.rst
TODO.md
debian8-dist.sh
setup.py
pyarm/__init__.py
pyarm/clock.py
pyarm/fig.py
pyarm.egg-info/PKG-INFO
pyarm.egg-info/SOURCES.txt
pyarm.egg-info/dependency_links.txt
pyarm.egg-info/requires.txt
pyarm.egg-info/top_level.txt
pyarm/agent/__init__.py
pyarm/agent/filereader.py
pyarm/agent/heaviside.py
pyarm/agent/ilqg6_agent.py
pyarm/agent/ilqg_agent.py
pyarm/agent/oscillator.py
pyarm/agent/random_oscillator.py
pyarm/agent/random_signal.py
pyarm/agent/sigmoid.py
pyarm/gui/__init__.py
pyarm/gui/abstract_gui.py
pyarm/gui/gtk_gui.py
pyarm/gui/none_gui.py
pyarm/gui/tkinter_gui.py
pyarm/model/__init__.py
pyarm/model/dirty_wrapper.py
pyarm/model/dirty_wrapper_6.py
pyarm/model/arm/__init__.py
pyarm/model/arm/abstract_arm_model.py
pyarm/model/arm/kambara_arm_model.py
pyarm/model/arm/mitrovic_arm_model.py
pyarm/model/arm/sagittal_arm_model.py
pyarm/model/arm/weiwei_arm_model.py
pyarm/model/kinematics/__init__.py
pyarm/model/kinematics/finite_difference_method.py
pyarm/model/muscle/__init__.py
pyarm/model/muscle/fake_muscle_model.py
pyarm/model/muscle/kambara_muscle_model.py
pyarm/model/muscle/mitrovic_muscle_model.py
pyarm/model/muscle/weiwei_muscle_model.py
scripts/pyarm
scripts/pyarm-plot
scripts/pyarm-test-model